setup.py
Sturzgefahr_dsnd_distributions/Binomialdistribution.py
Sturzgefahr_dsnd_distributions/Gaussiandistribution.py
Sturzgefahr_dsnd_distributions/Generaldistribution.py
Sturzgefahr_dsnd_distributions/__init__.py
Sturzgefahr_dsnd_distributions.egg-info/PKG-INFO
Sturzgefahr_dsnd_distributions.egg-info/SOURCES.txt
Sturzgefahr_dsnd_distributions.egg-info/dependency_links.txt
Sturzgefahr_dsnd_distributions.egg-info/not-zip-safe
Sturzgefahr_dsnd_distributions.egg-info/top_level.txt