Metadata-Version: 1.0
Name: Sturzgefahr-dsnd-distributions
Version: 0.1
Summary: Gaussian and Binomial distributions
Home-page: UNKNOWN
Author: Matthew Corsmeier
Author-email: matthew.corsmeier@gmail.com
License: UNKNOWN
Platform: UNKNOWN
